Proyecto_2/Kurt's_TB/Decoder.v
module decoder (input wire [6:0] address,
               output reg [12:0] data);

  always @ ( address ) begin
    casex (address)
    7'bxxxxxx0: data <= 13'b1000000001000;
    7'b00001x1: data <= 13'b0100000001000;
    7'b00000x1: data <= 13'b1000000001000;
    7'b00011x1: data <= 13'b1000000001000;
    7'b00010x1: data <= 13'b0100000001000;
    7'b0010xx1: data <= 13'b0001001000010;
    7'b0011xx1: data <= 13'b1001001100000;
    7'b0100xx1: data <= 13'b0011010000010;
    7'b0101xx1: data <= 13'b0011010000100;
    7'b0110xx1: data <= 13'b1011010100000;
    7'b0111xx1: data <= 13'b1000000111000;
    7'b1000x11: data <= 13'b0100000001000;
    7'b1000x01: data <= 13'b1000000001000;
    7'b1001x11: data <= 13'b1000000001000;
    7'b1001x01: data <= 13'b0100000001000;
    7'b1010xx1: data <= 13'b0011011000010;
    7'b1011xx1: data <= 13'b1011011100000;
    7'b1100xx1: data <= 13'b0100000001000;
    7'b1101xx1: data <= 13'b0000000001001;
    7'b1110xx1: data <= 13'b0011100000010;
    7'b1111xx1: data <= 13'b1011100100000;
    endcase
  end
endmodule

Proyecto_2/D_Flip_Flop.v
module D_Flip_Flop_1(input clk, reset, enable, d,
									   output reg q);
	always@(posedge clk, posedge reset)
	if (reset) q <= 0;
	else if (enable) q <= d;
	else q <= q;
endmodule

module D_Flip_Flop_2(input clk, reset, enable,
										 input [1:0] d,
									   output reg [1:0] q);
	always@(posedge clk, posedge reset)
	if (reset) q <= 0;
	else if (enable) q <= d;
	else q <= q;
endmodule

module D_Flip_Flop_4(input clk, reset, enable,
									   input [3:0] d,
									   output reg [3:0] q);
	always@(posedge clk, posedge reset)
	if (reset) q <= 3'b0;
	else if (enable) q <= d;
	else q <= q;
endmodule

module D_Flip_Flop_8(input clk, reset, enable,
									   input [7:0] d,
									   output reg [7:0] q);
	always@(posedge clk, posedge reset)
	if (reset) q <= 8'b0;
	else if (enable) q <= d;
	else q <= q;
endmodule

Proyecto_2/Kurt's_TB/T_Flip_Flop.v
module T_Flip_Flop (input clk, reset, enable,
                    output q);
  wire d;
  assign d = ~q;

      D_Flip_Flop_1 t(clk, reset, enable, d, q);

endmodule // T_Flip_Flop

Proyecto_2/TriState_buffer.v
module tri_state (input [3:0] a,
                  input s,
                  output [3:0] y);

    assign y = s ? a : 4'bzzzz;

endmodule

Proyecto_2/Kurt's_TB/ALU_Processor.v
module alu (input reset,
            input [3:0] a, b,
            input [2:0] f,
            output reg [3:0] y,
            output reg c_out, zero);


  parameter pass_a = 3'b000;
  parameter pass_b = 3'b010;
  parameter compare = 3'b001;
  parameter ADD = 3'b011;
  parameter NOR = 3'b100;

  always @(*) begin
    c_out = 0;
    case(f)
      pass_a: y = a;
      pass_b: y = b;
      compare: begin
            {c_out, y} = a-b;
                end
      ADD: begin
            {c_out, y} = a+b;
           end
      NOR: y = a~|b;
      default: y = 3'b000;
    endcase

  if (y == 0)
    zero = 1;
    else
      zero = 0;

  if (reset == 1)
    c_out = 0;
      end
endmodule // alu

Proyecto_2/Kurt's_TB/RAM.v
module RAM(input clk, we, cs,
           input [11:0] addr,
           input [3:0] din,
           output [3:0] dout);

  reg [3:0] mem [0:4095];

  always @ (posedge clk)
    if (cs&we) mem[addr] <= din;

  assign dout = (cs&~we) ? mem[addr] : 4'bzzzz;


endmodule

Proyecto_2/Kurt's_TB/ROM_Processor.v
module ROM (input [11:0] addr,
            output [7:0] y);

reg [7:0] rom [0:4095];

initial begin
  $readmemh ("memory.list", rom);
  end

  assign y = rom[addr];

endmodule

Proyecto_2/Contador.v
module contador (input clk, reset, enable, a,
                 input [0:11] load,
                 output reg [0:11] out);


  always @(posedge clk, posedge reset, posedge enable, posedge a)
    if (~enable)
      out <= out;
    else if (reset)
      out <= 12'b000000000000;
    else if (a&enable)
      out <= load;
    else if (enable)
      out <= out + 12'b000000000001;
endmodule // contador

Proyecto_2/uP.v
module uP(input clock, reset,
          input [3:0] pushbuttons,
          output phase, c_flag, z_flag,
          output [3:0] instr, oprnd, accu, data_bus, FF_out,
          output [7:0] program_byte,
          output [11:0] PC, address_RAM);

//Program Counter
  wire [11:0] PC;
  wire enable_counter, load_counter;
  contador counter(clock, reset, enable_counter, load_counter, address_RAM, PC);

//ROM
  wire [7:0] program_byte;
  ROM ROM(PC, program_byte);

//Fetch
  wire [3:0] instr, oprnd;
  D_Flip_Flop_8 fetch(clock, reset, ~phase, program_byte, {instr, oprnd});


//RAM
  wire [11:0] address_RAM;
  wire we, cs;
  assign address_RAM = {oprnd, program_byte};
  RAM RAM(clock, we, cs, address_RAM, data_bus, data_bus);

//Bus1
  wire [3:0] data_bus;
  wire enable_bus1;
  tri_state bus1(oprnd, enable_bus1, data_bus);

//ALU
  wire [3:0] accu, alu_out;
  wire [2:0] f;
  wire c, zero;
  D_Flip_Flop_4 accumulator(clock, reset, enable_accu, alu_out, accu);
  alu alu (reset, accu, data_bus, f, alu_out, c, zero);

//bus2
  wire enable_bus2;
  tri_state bus2(alu_out, enable_bus2, data_bus);

//inputs
  wire enable_in;
  tri_state in(pushbuttons, enable_in, data_bus);

//outputs
wire enable_out;
  D_Flip_Flop_4 out(clock, reset, enable_out, data_bus, FF_out);

//phase
  wire phase;
  wire enable_phase;
  T_Flip_Flop PHASE(clock, reset, 1'b1, phase);

//decoder
  wire [1:0] flags;
  wire enable_flags, c_flag, z_flag;
  assign c_flag = flags[1];
  assign z_flag = flags[0];
  D_Flip_Flop_2 FLAGS(clock, reset, enable_flags, {c, zero}, flags);
  decoder decoder({instr, flags, phase}, {enable_counter, load_counter, enable_accu,
                  enable_flags, f[2], f[1], f[0], cs, we, enable_bus2,
                  enable_in, enable_bus1, enable_out});
endmodule

Proyecto_2/Stefano's_TB/uP_tb.v
module testbench();
  reg clock, reset;
  reg [3:0] pushbuttons;
  wire phase, c_flag, z_flag;
  wire [3:0] instr, oprnd, accu, data_bus, FF_out;
  wire [7:0] program_byte;
  wire [11:0] PC, address_RAM;

  uP uP(.clock(clock),
              .reset(reset),
              .pushbuttons(pushbuttons),
              .phase(phase),
              .c_flag(c_flag),
              .z_flag(z_flag),
              .instr(instr),
              .oprnd(oprnd),
              .accu(accu),
              .data_bus(data_bus),
              .FF_out(FF_out),
              .program_byte(program_byte),
              .PC(PC),
              .address_RAM(address_RAM));

  initial
    #750 $finish;

  always
    #5 clock = ~clock;

  initial begin
    clock = 0; reset = 0; pushbuttons = 4'b0110;
    #2 reset = 1;
    #1 reset = 0;
  end

    initial begin
      $dumpfile("uP_tb.vcd");
      $dumpvars(0, testbench);
      end
endmodule

Proyecto_2/Stefano's_TB/uP_tb.vcd
$date
	Sun Nov 22 21:40:31 2020
$end
$version
	Icarus Verilog
$end
$timescale
	1ps
$end
$scope module testbench $end
$var wire 4 ! data_bus [3:0] $end
$var wire 1 " z_flag $end
$var wire 8 # program_byte [7:0] $end
$var wire 1 $ phase $end
$var wire 4 % oprnd [3:0] $end
$var wire 4 & instr [3:0] $end
$var wire 1 ' c_flag $end
$var wire 12 ( address_RAM [11:0] $end
$var wire 4 ) accu [3:0] $end
$var wire 12 * PC [11:0] $end
$var wire 4 + FF_out [3:0] $end
$var reg 1 , clock $end
$var reg 4 - pushbuttons [3:0] $end
$var reg 1 . reset $end
$scope module uP $end
$var wire 1 , clock $end
$var wire 4 / data_bus [3:0] $end
$var wire 4 0 pushbuttons [3:0] $end
$var wire 1 . reset $end
$var wire 1 1 zero $end
$var wire 1 " z_flag $end
$var wire 1 2 we $end
$var wire 8 3 program_byte [7:0] $end
$var wire 1 $ phase $end
$var wire 4 4 oprnd [3:0] $end
$var wire 1 5 load_counter $end
$var wire 4 6 instr [3:0] $end
$var wire 2 7 flags [1:0] $end
$var wire 3 8 f [2:0] $end
$var wire 1 9 enable_out $end
$var wire 1 : enable_in $end
$var wire 1 ; enable_flags $end
$var wire 1 < enable_counter $end
$var wire 1 = enable_bus2 $end
$var wire 1 > enable_bus1 $end
$var wire 1 ? enable_accu $end
$var wire 1 @ cs $end
$var wire 1 ' c_flag $end
$var wire 1 A c $end
$var wire 4 B alu_out [3:0] $end
$var wire 12 C address_RAM [11:0] $end
$var wire 4 D accu [3:0] $end
$var wire 12 E PC [11:0] $end
$var wire 4 F FF_out [3:0] $end
$scope module FLAGS $end
$var wire 1 , clk $end
$var wire 2 G d [1:0] $end
$var wire 1 ; enable $end
$var wire 1 . reset $end
$var reg 2 H q [1:0] $end
$upscope $end
$scope module PHASE $end
$var wire 1 , clk $end
$var wire 1 I d $end
$var wire 1 J enable $end
$var wire 1 . reset $end
$var wire 1 $ q $end
$scope module t $end
$var wire 1 , clk $end
$var wire 1 I d $end
$var wire 1 J enable $end
$var wire 1 . reset $end
$var reg 1 $ q $end
$upscope $end
$upscope $end
$scope module RAM $end
$var wire 12 K addr [11:0] $end
$var wire 1 , clk $end
$var wire 1 @ cs $end
$var wire 4 L din [3:0] $end
$var wire 4 M dout [3:0] $end
$var wire 1 2 we $end
$upscope $end
$scope module ROM $end
$var wire 8 N y [7:0] $end
$var wire 12 O addr [11:0] $end
$upscope $end
$scope module accumulator $end
$var wire 1 , clk $end
$var wire 1 ? enable $end
$var wire 1 . reset $end
$var wire 4 P d [3:0] $end
$var reg 4 Q q [3:0] $end
$upscope $end
$scope module alu $end
$var wire 4 R a [3:0] $end
$var wire 4 S b [3:0] $end
$var wire 3 T f [2:0] $end
$var wire 1 . reset $end
$var reg 1 A c_out $end
$var reg 4 U y [3:0] $end
$var reg 1 1 zero $end
$upscope $end
$scope module bus1 $end
$var wire 4 V a [3:0] $end
$var wire 1 > s $end
$var wire 4 W y [3:0] $end
$upscope $end
$scope module bus2 $end
$var wire 4 X a [3:0] $end
$var wire 1 = s $end
$var wire 4 Y y [3:0] $end
$upscope $end
$scope module counter $end
$var wire 1 5 a $end
$var wire 1 , clk $end
$var wire 1 < enable $end
$var wire 12 Z load [0:11] $end
$var wire 1 . reset $end
$var reg 12 [ out [0:11] $end
$upscope $end
$scope module decoder $end
$var wire 7 \ address [6:0] $end
$var reg 13 ] data [12:0] $end
$upscope $end
$scope module fetch $end
$var wire 1 , clk $end
$var wire 8 ^ d [7:0] $end
$var wire 1 _ enable $end
$var wire 1 . reset $end
$var reg 8 ` q [7:0] $end
$upscope $end
$scope module in $end
$var wire 4 a a [3:0] $end
$var wire 1 : s $end
$var wire 4 b y [3:0] $end
$upscope $end
$scope module out $end
$var wire 1 , clk $end
$var wire 4 c d [3:0] $end
$var wire 1 9 enable $end
$var wire 1 . reset $end
$var reg 4 d q [3:0] $end
$upscope $end
$upscope $end
$upscope $end
$enddefinitions $end
#0
$dumpvars
bx d
bx c
bx b
b110 a
bx `
x_
bx ^
bx ]
bx \
bx [
bx Z
bx Y
b0 X
bx W
bx V
b0 U
bx T
bx S
bx R
bx Q
b0 P
bx O
bx N
bx M
bx L
bx K
1J
xI
bx H
b1 G
bx F
bx E
bx D
bx C
b0 B
0A
x@
x?
x>
x=
x<
x;
x:
x9
bx 8
bx 7
bx 6
x5
bx 4
bx 3
x2
11
b110 0
bx /
0.
b110 -
0,
bx +
bx *
bx )
bx (
x'
bx &
bx %
x$
bx #
x"
bx !
$end
#2
b0 !
b0 /
b0 L
b0 M
b0 S
b0 W
b0 Y
b0 b
b0 c
09
0>
0:
1=
02
0@
b0 8
b0 T
0;
0?
05
1<
b1000000001000 ]
b0 %
b0 4
b0 V
b0 &
b0 6
1I
1_
0"
0'
b1001100 (
b1001100 C
b1001100 K
b1001100 Z
b1001100 #
b1001100 3
b1001100 N
b1001100 ^
b0 *
b0 E
b0 O
b0 [
b0 `
b0 )
b0 D
b0 Q
b0 R
b0 +
b0 F
b0 d
0$
b0 \
b0 7
b0 H
1.
#3
0.
#5
b0 G
01
b1100 B
b1100 P
b1100 U
b1100 X
b1100 !
b1100 /
b1100 L
b1100 M
b1100 S
b1100 W
b1100 Y
b1100 b
b1100 c
1>
0=
b10 8
b10 T
1;
1?
0<
b11010000010 ]
0I
0_
b1100 %
b1100 4
b1100 V
b100 &
b100 6
b100001 \
1$
b1001100 `
b110000101010 (
b110000101010 C
b110000101010 K
b110000101010 Z
b101010 #
b101010 3
b101010 N
b101010 ^
b1 *
b1 E
b1 O
b1 [
1,
#10
0,
#15
0>
1=
b0 8
b0 T
0;
0?
1<
b1000000001000 ]
1I
1_
b1100 )
b1100 D
b1100 Q
b1100 R
b100000 \
0$
1,
#20
0,
#25
b1010 !
b1010 /
b1010 L
b1010 M
b1010 S
b1010 W
b1010 Y
b1010 b
b1010 c
b0 G
01
b10 B
b10 P
b10 U
b10 X
1>
0=
b1 8
b1 T
1;
0<
b1001000010 ]
0I
0_
b1010 %
b1010 4
b1010 V
b10 &
b10 6
b10001 \
1$
b101010 `
b101000101111 (
b101000101111 C
b101000101111 K
b101000101111 Z
b101111 #
b101111 3
b101111 N
b101111 ^
b10 *
b10 E
b10 O
b10 [
1,
#30
0,
#35
b1100 !
b1100 /
b1100 L
b1100 M
b1100 S
b1100 W
b1100 Y
b1100 b
b1100 c
b1100 B
b1100 P
b1100 U
b1100 X
0>
1=
b0 8
b0 T
0;
1<
b1000000001000 ]
1I
1_
b10000 \
0$
1,
#40
0,
#45
1A
b1111 !
b1111 /
b1111 L
b1111 M
b1111 S
b1111 W
b1111 Y
b1111 b
b1111 c
b10 G
01
b1101 B
b1101 P
b1101 U
b1101 X
1>
0=
b1 8
b1 T
1;
0<
b1001000010 ]
0I
0_
b1111 %
b1111 4
b1111 V
b10001 \
1$
b101111 `
b111110100001 (
b111110100001 C
b111110100001 K
b111110100001 Z
b10100001 #
b10100001 3
b10100001 N
b10100001 ^
b11 *
b11 E
b11 O
b11 [
1,
#50
0,
#55
b1100 !
b1100 /
b1100 L
b1100 M
b1100 S
b1100 W
b1100 Y
b1100 b
b1100 c
b1100 B
b1100 P
b1100 U
b1100 X
b0 G
0A
0>
1=
b0 8
b0 T
0;
1<
b1000000001000 ]
1I
1_
1'
0$
b10100 \
b10 7
b10 H
1,
#60
0,
#65
b1 !
b1 /
b1 L
b1 M
b1 S
b1 W
b1 Y
b1 b
b1 c
b0 G
0A
b1101 B
b1101 P
b1101 U
b1101 X
1>
0=
b11 8
b11 T
1;
1?
0<
b11011000010 ]
0I
0_
b1 %
b1 4
b1 V
b1010 &
b1010 6
b1010101 \
1$
b10100001 `
b110100011 (
b110100011 C
b110100011 K
b110100011 Z
b10100011 #
b10100011 3
b10100011 N
b10100011 ^
b100 *
b100 E
b100 O
b100 [
1,
#70
0,
#75
b1101 !
b1101 /
b1101 L
b1101 M
b1101 S
b1101 W
b1101 Y
b1101 b
b1101 c
0>
1=
b0 8
b0 T
0;
0?
1<
b1000000001000 ]
b1101 B
b1101 P
b1101 U
b1101 X
1I
1_
0'
b1101 )
b1101 D
b1101 Q
b1101 R
0$
b1010000 \
b0 7
b0 H
1,
#80
0,
#85
11
b11 !
b11 /
b11 L
b11 M
b11 S
b11 W
b11 Y
b11 b
b11 c
b11 G
1A
b0 B
b0 P
b0 U
b0 X
1>
0=
b11 8
b11 T
1;
1?
0<
b11011000010 ]
0I
0_
b11 %
b11 4
b11 V
b1010001 \
1$
b10100011 `
b1101000111 (
b1101000111 C
b1101000111 K
b1101000111 Z
b1000111 #
b1000111 3
b1000111 N
b1000111 ^
b101 *
b101 E
b101 O
b101 [
1,
#90
0,
#95
b0 !
b0 /
b0 L
b0 M
b0 S
b0 W
b0 Y
b0 b
b0 c
0>
1=
b0 8
b0 T
0;
0?
1<
b1000000001000 ]
11
b0 B
b0 P
b0 U
b0 X
b1 G
0A
1I
1_
1"
1'
b0 )
b0 D
b0 Q
b0 R
0$
b1010110 \
b11 7
b11 H
1,
#100
0,
#105
b0 G
01
b111 B
b111 P
b111 U
b111 X
b111 !
b111 /
b111 L
b111 M
b111 S
b111 W
b111 Y
b111 b
b111 c
1>
0=
b10 8
b10 T
1;
1?
0<
b11010000010 ]
0I
0_
b111 %
b111 4
b111 V
b100 &
b100 6
b100111 \
1$
b1000111 `
b11111100010 (
b11111100010 C
b11111100010 K
b11111100010 Z
b11100010 #
b11100010 3
b11100010 N
b11100010 ^
b110 *
b110 E
b110 O
b110 [
1,
#110
0,
#115
0>
1=
b0 8
b0 T
0;
0?
1<
b1000000001000 ]
1I
1_
0"
0'
b111 )
b111 D
b111 Q
b111 R
0$
b100000 \
b0 7
b0 H
1,
#120
0,
#125
b10 !
b10 /
b10 L
b10 M
b10 S
b10 W
b10 Y
b10 b
b10 c
b1000 B
b1000 P
b1000 U
b1000 X
1>
0=
b100 8
b100 T
1;
1?
0<
b11100000010 ]
0I
0_
b10 %
b10 4
b10 V
b1110 &
b1110 6
b1110001 \
1$
b11100010 `
b1001001111 (
b1001001111 C
b1001001111 K
b1001001111 Z
b1001111 #
b1001111 3
b1001111 N
b1001111 ^
b111 *
b111 E
b111 O
b111 [
1,
#130
0,
#135
b1000 !
b1000 /
b1000 L
b1000 M
b1000 S
b1000 W
b1000 Y
b1000 b
b1000 c
0>
1=
b0 8
b0 T
0;
0?
1<
b1000000001000 ]
b1000 B
b1000 P
b1000 U
b1000 X
1I
1_
b1000 )
b1000 D
b1000 Q
b1000 R
b1110000 \
0$
1,
#140
0,
#145
b1111 B
b1111 P
b1111 U
b1111 X
b1111 !
b1111 /
b1111 L
b1111 M
b1111 S
b1111 W
b1111 Y
b1111 b
b1111 c
1>
0=
b10 8
b10 T
1;
1?
0<
b11010000010 ]
0I
0_
b1111 %
b1111 4
b1111 V
b100 &
b100 6
b100001 \
1$
b1001111 `
b111101110000 (
b111101110000 C
b111101110000 K
b111101110000 Z
b1110000 #
b1110000 3
b1110000 N
b1110000 ^
b1000 *
b1000 E
b1000 O
b1000 [
1,
#150
0,
#155
0>
1=
b0 8
b0 T
0;
0?
1<
b1000000001000 ]
1I
1_
b1111 )
b1111 D
b1111 Q
b1111 R
b100000 \
0$
1,
#160
0,
#165
b1111 !
b1111 /
b1111 L
b1111 M
b1111 S
b1111 W
b1111 Y
b1111 b
b1111 c
12
1@
b1000000111000 ]
0I
0_
b0 %
b0 4
b0 V
b111 &
b111 6
b111001 \
1$
b1110000 `
b0 (
b0 C
b0 K
b0 Z
b0 #
b0 3
b0 N
b0 ^
b1001 *
b1001 E
b1001 O
b1001 [
1,
#170
0,
#175
02
0@
b1000000001000 ]
1I
1_
b1000101 (
b1000101 C
b1000101 K
b1000101 Z
b1000101 #
b1000101 3
b1000101 N
b1000101 ^
b1010 *
b1010 E
b1010 O
b1010 [
b111000 \
0$
1,
#180
0,
#185
b101 B
b101 P
b101 U
b101 X
b101 !
b101 /
b101 L
b101 M
b101 S
b101 W
b101 Y
b101 b
b101 c
1>
0=
b10 8
b10 T
1;
1?
0<
b11010000010 ]
0I
0_
b101 %
b101 4
b101 V
b100 &
b100 6
b100001 \
1$
b1000101 `
b10101110001 (
b10101110001 C
b10101110001 K
b10101110001 Z
b1110001 #
b1110001 3
b1110001 N
b1110001 ^
b1011 *
b1011 E
b1011 O
b1011 [
1,
#190
0,
#195
0>
1=
b0 8
b0 T
0;
0?
1<
b1000000001000 ]
1I
1_
b101 )
b101 D
b101 Q
b101 R
b100000 \
0$
1,
#200
0,
#205
b101 !
b101 /
b101 L
b101 M
b101 S
b101 W
b101 Y
b101 b
b101 c
12
1@
b1000000111000 ]
0I
0_
b1 %
b1 4
b1 V
b111 &
b111 6
b111001 \
1$
b1110001 `
b100010001 (
b100010001 C
b100010001 K
b100010001 Z
b10001 #
b10001 3
b10001 N
b10001 ^
b1100 *
b1100 E
b1100 O
b1100 [
1,
#210
0,
#215
02
0@
b1000000001000 ]
1I
1_
b101100000 (
b101100000 C
b101100000 K
b101100000 Z
b1100000 #
b1100000 3
b1100000 N
b1100000 ^
b1101 *
b1101 E
b1101 O
b1101 [
b111000 \
0$
1,
#220
0,
#225
b1111 B
b1111 P
b1111 U
b1111 X
b1111 !
b1111 /
b1111 L
b1111 M
b1111 S
b1111 W
b1111 Y
b1111 b
b1111 c
0=
1@
b10 8
b10 T
1;
1?
b1011010100000 ]
0I
0_
b0 %
b0 4
b0 V
b110 &
b110 6
b110001 \
1$
b1100000 `
b0 (
b0 C
b0 K
b0 Z
b0 #
b0 3
b0 N
b0 ^
b1110 *
b1110 E
b1110 O
b1110 [
1,
#230
0,
#235
1=
0@
b0 8
b0 T
0;
0?
b1000000001000 ]
b1111 B
b1111 P
b1111 U
b1111 X
b1111 !
b1111 /
b1111 L
b1111 M
b1111 S
b1111 W
b1111 Y
b1111 b
b1111 c
1I
1_
b1100001 (
b1100001 C
b1100001 K
b1100001 Z
b1100001 #
b1100001 3
b1100001 N
b1100001 ^
b1111 *
b1111 E
b1111 O
b1111 [
b1111 )
b1111 D
b1111 Q
b1111 R
b110000 \
0$
1,
#240
0,
#245
b101 B
b101 P
b101 U
b101 X
b101 !
b101 /
b101 L
b101 M
b101 S
b101 W
b101 Y
b101 b
b101 c
0=
1@
b10 8
b10 T
1;
1?
b1011010100000 ]
0I
0_
b1 %
b1 4
b1 V
b110001 \
1$
b1100001 `
b100010001 (
b100010001 C
b100010001 K
b100010001 Z
b10001 #
b10001 3
b10001 N
b10001 ^
b10000 *
b10000 E
b10000 O
b10000 [
1,
#250
0,
#255
1=
0@
b0 8
b0 T
0;
0?
b1000000001000 ]
b101 B
b101 P
b101 U
b101 X
b101 !
b101 /
b101 L
b101 M
b101 S
b101 W
b101 Y
b101 b
b101 c
1I
1_
b101001000 (
b101001000 C
b101001000 K
b101001000 Z
b1001000 #
b1001000 3
b1001000 N
b1001000 ^
b10001 *
b10001 E
b10001 O
b10001 [
b101 )
b101 D
b101 Q
b101 R
b110000 \
0$
1,
#260
0,
#265
b1000 B
b1000 P
b1000 U
b1000 X
b1000 !
b1000 /
b1000 L
b1000 M
b1000 S
b1000 W
b1000 Y
b1000 b
b1000 c
1>
0=
b10 8
b10 T
1;
1?
0<
b11010000010 ]
0I
0_
b1000 %
b1000 4
b1000 V
b100 &
b100 6
b100001 \
1$
b1001000 `
b100000110000 (
b100000110000 C
b100000110000 K
b100000110000 Z
b110000 #
b110000 3
b110000 N
b110000 ^
b10010 *
b10010 E
b10010 O
b10010 [
1,
#270
0,
#275
0>
1=
b0 8
b0 T
0;
0?
1<
b1000000001000 ]
1I
1_
b1000 )
b1000 D
b1000 Q
b1000 R
b100000 \
0$
1,
#280
0,
#285
1A
b1111 !
b1111 /
b1111 L
b1111 M
b1111 S
b1111 W
b1111 Y
b1111 b
b1111 c
b10 G
01
b1001 B
b1001 P
b1001 U
b1001 X
0=
1@
b1 8
b1 T
1;
b1001001100000 ]
0I
0_
b0 %
b0 4
b0 V
b11 &
b11 6
b11001 \
1$
b110000 `
b0 (
b0 C
b0 K
b0 Z
b0 #
b0 3
b0 N
b0 ^
b10011 *
b10011 E
b10011 O
b10011 [
1,
#290
0,
#295
1=
0@
b0 8
b0 T
0;
b1000000001000 ]
b1000 B
b1000 P
b1000 U
b1000 X
b0 G
0A
b1000 !
b1000 /
b1000 L
b1000 M
b1000 S
b1000 W
b1000 Y
b1000 b
b1000 c
1I
1_
1'
b1000110 (
b1000110 C
b1000110 K
b1000110 Z
b1000110 #
b1000110 3
b1000110 N
b1000110 ^
b10100 *
b10100 E
b10100 O
b10100 [
0$
b11100 \
b10 7
b10 H
1,
#300
0,
#305
b110 B
b110 P
b110 U
b110 X
b110 !
b110 /
b110 L
b110 M
b110 S
b110 W
b110 Y
b110 b
b110 c
1>
0=
b10 8
b10 T
1;
1?
0<
b11010000010 ]
0I
0_
b110 %
b110 4
b110 V
b100 &
b100 6
b100101 \
1$
b1000110 `
b11000110001 (
b11000110001 C
b11000110001 K
b11000110001 Z
b110001 #
b110001 3
b110001 N
b110001 ^
b10101 *
b10101 E
b10101 O
b10101 [
1,
#310
0,
#315
0>
1=
b0 8
b0 T
0;
0?
1<
b1000000001000 ]
1I
1_
0'
b110 )
b110 D
b110 Q
b110 R
0$
b100000 \
b0 7
b0 H
1,
#320
0,
#325
b101 !
b101 /
b101 L
b101 M
b101 S
b101 W
b101 Y
b101 b
b101 c
b0 G
01
b1 B
b1 P
b1 U
b1 X
0=
1@
b1 8
b1 T
1;
b1001001100000 ]
0I
0_
b1 %
b1 4
b1 V
b11 &
b11 6
b11001 \
1$
b110001 `
b100010001 (
b100010001 C
b100010001 K
b100010001 Z
b10001 #
b10001 3
b10001 N
b10001 ^
b10110 *
b10110 E
b10110 O
b10110 [
1,
#330
0,
#335
1=
0@
b0 8
b0 T
0;
b1000000001000 ]
b0 G
0A
b110 B
b110 P
b110 U
b110 X
b110 !
b110 /
b110 L
b110 M
b110 S
b110 W
b110 Y
b110 b
b110 c
1I
1_
b110110000 (
b110110000 C
b110110000 K
b110110000 Z
b10110000 #
b10110000 3
b10110000 N
b10110000 ^
b10111 *
b10111 E
b10111 O
b10111 [
b11000 \
0$
1,
#340
0,
#345
b10 G
1A
b1111 !
b1111 /
b1111 L
b1111 M
b1111 S
b1111 W
b1111 Y
b1111 b
b1111 c
b101 B
b101 P
b101 U
b101 X
0=
1@
b11 8
b11 T
1;
1?
b1011011100000 ]
0I
0_
b0 %
b0 4
b0 V
b1011 &
b1011 6
b1011001 \
1$
b10110000 `
b0 (
b0 C
b0 K
b0 Z
b0 #
b0 3
b0 N
b0 ^
b11000 *
b11000 E
b11000 O
b11000 [
1,
#350
0,
#355
1=
0@
b0 8
b0 T
0;
0?
b1000000001000 ]
b101 !
b101 /
b101 L
b101 M
b101 S
b101 W
b101 Y
b101 b
b101 c
b101 B
b101 P
b101 U
b101 X
b0 G
0A
1I
1_
1'
b10110001 (
b10110001 C
b10110001 K
b10110001 Z
b10110001 #
b10110001 3
b10110001 N
b10110001 ^
b11001 *
b11001 E
b11001 O
b11001 [
b101 )
b101 D
b101 Q
b101 R
0$
b1011100 \
b10 7
b10 H
1,
#360
0,
#365
b101 !
b101 /
b101 L
b101 M
b101 S
b101 W
b101 Y
b101 b
b101 c
b1010 B
b1010 P
b1010 U
b1010 X
0=
1@
b11 8
b11 T
1;
1?
b1011011100000 ]
0I
0_
b1 %
b1 4
b1 V
b1011101 \
1$
b10110001 `
b100010001 (
b100010001 C
b100010001 K
b100010001 Z
b10001 #
b10001 3
b10001 N
b10001 ^
b11010 *
b11010 E
b11010 O
b11010 [
1,
#370
0,
#375
1=
0@
b0 8
b0 T
0;
0?
b1000000001000 ]
b0 G
0A
b1010 !
b1010 /
b1010 L
b1010 M
b1010 S
b1010 W
b1010 Y
b1010 b
b1010 c
b1010 B
b1010 P
b1010 U
b1010 X
1I
1_
0'
b111110001 (
b111110001 C
b111110001 K
b111110001 Z
b11110001 #
b11110001 3
b11110001 N
b11110001 ^
b11011 *
b11011 E
b11011 O
b11011 [
b1010 )
b1010 D
b1010 Q
b1010 R
0$
b1011000 \
b0 7
b0 H
1,
#380
0,
#385
b1 G
11
b101 !
b101 /
b101 L
b101 M
b101 S
b101 W
b101 Y
b101 b
b101 c
b0 B
b0 P
b0 U
b0 X
0=
1@
b100 8
b100 T
1;
1?
b1011100100000 ]
0I
0_
b1111 &
b1111 6
b1111001 \
1$
b11110001 `
b100010001 (
b100010001 C
b100010001 K
b100010001 Z
b10001 #
b10001 3
b10001 N
b10001 ^
b11100 *
b11100 E
b11100 O
b11100 [
1,
#390
0,
#395
1=
0@
b0 8
b0 T
0;
0?
b1000000001000 ]
b0 !
b0 /
b0 L
b0 M
b0 S
b0 W
b0 Y
b0 b
b0 c
b1 G
11
b0 B
b0 P
b0 U
b0 X
1I
1_
1"
b110010000 (
b110010000 C
b110010000 K
b110010000 Z
b10010000 #
b10010000 3
b10010000 N
b10010000 ^
b11101 *
b11101 E
b11101 O
b11101 [
b0 )
b0 D
b0 Q
b0 R
0$
b1111010 \
b1 7
b1 H
1,
#400
0,
#405
0I
0_
b0 %
b0 4
b0 V
b1001 &
b1001 6
b1001011 \
1$
b10010000 `
b1010000 (
b1010000 C
b1010000 K
b1010000 Z
b1010000 #
b1010000 3
b1010000 N
b1010000 ^
b11110 *
b11110 E
b11110 O
b11110 [
1,
#410
0,
#415
1I
1_
b1000000 (
b1000000 C
b1000000 K
b1000000 Z
b1000000 #
b1000000 3
b1000000 N
b1000000 ^
b11111 *
b11111 E
b11111 O
b11111 [
b1001010 \
0$
1,
#420
0,
#425
b0 !
b0 /
b0 L
b0 M
b0 S
b0 W
b0 Y
b0 b
b0 c
1>
0=
b10 8
b10 T
1;
1?
0<
b11010000010 ]
0I
0_
b100 &
b100 6
b100011 \
1$
b1000000 `
b10000001 (
b10000001 C
b10000001 K
b10000001 Z
b10000001 #
b10000001 3
b10000001 N
b10000001 ^
b100000 *
b100000 E
b100000 O
b100000 [
1,
#430
0,
#435
0>
1=
b0 8
b0 T
0;
0?
1<
b1000000001000 ]
1I
1_
b100010 \
0$
1,
#440
0,
#445
15
0<
b100000001000 ]
0I
0_
b1 %
b1 4
b1 V
b1000 &
b1000 6
b1000011 \
1$
b10000001 `
b100000000 (
b100000000 C
b100000000 K
b100000000 Z
b0 #
b0 3
b0 N
b0 ^
b100001 *
b100001 E
b100001 O
b100001 [
1,
#450
0,
#455
05
1<
b1000000001000 ]
1I
1_
b101000100 (
b101000100 C
b101000100 K
b101000100 Z
b1000100 #
b1000100 3
b1000100 N
b1000100 ^
b100000000 *
b100000000 E
b100000000 O
b100000000 [
b1000010 \
0$
1,
#460
0,
