Lab09/Ejercicio5/Ejercicio5.v
module caseRom (input wire [6:0] address,
               output reg [12:0] data);

  always @ ( address ) begin
    casex (address)
    7'bxxxxxx0: data <= 13'b1000000001000;
    7'b00001x1: data <= 13'b0100000001000;
    7'b00000x1: data <= 13'b1000000001000;
    7'b00011x1: data <= 13'b1000000001000;
    7'b00010x1: data <= 13'b0100000001000;
    7'b0010xx1: data <= 13'b0001001000010;
    7'b0011xx1: data <= 13'b1001001100000;
    7'b0100xx1: data <= 13'b0011010000010;
    7'b0101xx1: data <= 13'b0011010000100;
    7'b0110xx1: data <= 13'b1011010100000;
    7'b0111xx1: data <= 13'b1000000111000;
    7'b1000x11: data <= 13'b0100000001000;
    7'b1000x01: data <= 13'b1000000001000;
    7'b1001x11: data <= 13'b1000000001000;
    7'b1001x01: data <= 13'b0100000001000;
    7'b1010xx1: data <= 13'b0011011000010;
    7'b1011xx1: data <= 13'b1011011100000;
    7'b1100xx1: data <= 13'b0100000001000;
    7'b1101xx1: data <= 13'b0000000001001;
    7'b1110xx1: data <= 13'b0011100000010;
    7'b1111xx1: data <= 13'b1011100100000;
    endcase
  end
endmodule

Lab09/Ejercicio5/Ejercicio5_tb.v
module ejercicio5_tb ();
  reg [6:0] address;
  wire [12:0] data;

  caseRom caseRom(address, data);

  initial begin
  $display("Tristate Buffer");
  $display("time\t\tadress\t|\tdata");
  $display("------------------");
  $monitor("%g\t\t%b\t|\t%b",
    $time, address, data);
  #5 address = 7'bxxxxxx0;
  #5 address = 7'b00001x1;
  #5 address = 7'b00000x1;
  #5 address = 7'b00011x1;
  #5 address = 7'b00010x1;
  #5 address = 7'b0010xx1;
  #5 address = 7'b0011xx1;
  #5 address = 7'b0100xx1;
  #5 address = 7'b0101xx1;
  #5 address = 7'b0110xx1;
  #5 address = 7'b0111xx1;
  #5 address = 7'b1000x11;
  #5 address = 7'b1000x01;
  #5 address = 7'b1001x11;
  #5 address = 7'b1001x01;
  #5 address = 7'b1010xx1;
  #5 address = 7'b1011xx1;
  #5 address = 7'b1100xx1;
  #5 address = 7'b1101xx1;
  #5 address = 7'b1110xx1;
  #5 address = 7'b1111xx1;
  #5$display("Probando Don't Cares");
  #5 address = 7'b0000000;
  #5 address = 7'b0101010;
  #5 address = 7'b1010100;
  #5 address = 7'b0001101;
  #5 address = 7'b0100101;
  #5 address = 7'b0100101;
  #5 $finish;
  end

  initial begin
  $dumpfile("ejercicio5_tb.vcd");
  $dumpvars(0, ejercicio5_tb);
  end

endmodule

Lab09/Ejercicio5/ejercicio5_tb.vcd
$date
	Fri Oct 30 23:22:57 2020
$end
$version
	Icarus Verilog
$end
$timescale
	1ps
$end
$scope module ejercicio5_tb $end
$var wire 13 ! data [12:0] $end
$var reg 7 " address [6:0] $end
$scope module caseRom $end
$var wire 7 # address [6:0] $end
$var reg 13 $ data [12:0] $end
$upscope $end
$upscope $end
$enddefinitions $end
#0
$dumpvars
bx $
bx #
bx "
bx !
$end
#5
b1000000001000 !
b1000000001000 $
bx0 "
bx0 #
#10
b100000001000 !
b100000001000 $
b1x1 "
b1x1 #
#15
b1000000001000 !
b1000000001000 $
b0x1 "
b0x1 #
#20
b11x1 "
b11x1 #
#25
b100000001000 !
b100000001000 $
b10x1 "
b10x1 #
#30
b1001000010 !
b1001000010 $
b10xx1 "
b10xx1 #
#35
b1001001100000 !
b1001001100000 $
b11xx1 "
b11xx1 #
#40
b11010000010 !
b11010000010 $
b100xx1 "
b100xx1 #
#45
b11010000100 !
b11010000100 $
b101xx1 "
b101xx1 #
#50
b1011010100000 !
b1011010100000 $
b110xx1 "
b110xx1 #
#55
b1000000111000 !
b1000000111000 $
b111xx1 "
b111xx1 #
#60
b100000001000 !
b100000001000 $
b1000x11 "
b1000x11 #
#65
b1000000001000 !
b1000000001000 $
b1000x01 "
b1000x01 #
#70
b1001x11 "
b1001x11 #
#75
b100000001000 !
b100000001000 $
b1001x01 "
b1001x01 #
#80
b11011000010 !
b11011000010 $
b1010xx1 "
b1010xx1 #
#85
b1011011100000 !
b1011011100000 $
b1011xx1 "
b1011xx1 #
#90
b100000001000 !
b100000001000 $
b1100xx1 "
b1100xx1 #
#95
b1001 !
b1001 $
b1101xx1 "
b1101xx1 #
#100
b11100000010 !
b11100000010 $
b1110xx1 "
b1110xx1 #
#105
b1011100100000 !
b1011100100000 $
b1111xx1 "
b1111xx1 #
#115
b1000000001000 !
b1000000001000 $
b0 "
b0 #
#120
b101010 "
b101010 #
#125
b1010100 "
b1010100 #
#130
b1101 "
b1101 #
#135
b11010000010 !
b11010000010 $
b100101 "
b100101 #
