Lab09/Ejercicio1/Ejercicio1.v
module D_Flip_Flop (input clk, enable, reset, d,
                    output reg q);
  always @ (posedge clk, posedge reset, posedge enable)
    if (~enable)
      q = q;
    else if (reset)
      q = 0;
    else
      q = d;
endmodule // DFlip-Flop

module D_Flip_Flop_2bits (input clk, enable, reset,
                         input [1:0] d,
                         output [1:0] q);
  D_Flip_Flop B1(clk, enable, reset, d[1], q[1]);
  D_Flip_Flop B0(clk, enable, reset, d[0], q[0]);
endmodule // 2_Bit_D_Flip_Flop

module D_Flip_Flop_4bits (input  clk, enable, reset,
                          input [3:0] d,
                          output [3:0] q);
  D_Flip_Flop_2bits B32(clk, enable, reset, d[3:2], q[3:2]);
  D_Flip_Flop_2bits B10(clk, enable, reset, d[1:0], q[1:0]);
endmodule // D_Flip_Flop_4bits

Lab09/Ejercicio1/Ejercicio1_tb.v
module ejercicio1_tb ();
  reg clk, enable, reset, d;
  reg [1:0] d2;
  reg [3:0] d4;
  wire q;
  wire [1:0] q2;
  wire [3:0] q4;

  D_Flip_Flop D_Flip_Flop(clk, enable, reset, d, q);
  D_Flip_Flop_2bits D_Flip_Flop_2bits(clk, enable, reset, d2, q2);
  D_Flip_Flop_4bits D_Flip_Flop_4bits(clk, enable, reset, d4, q4);

  always begin
    #5 clk = ~clk;
  end

  initial begin
  $display("Flip Flop Tipo D - 1 Bit");
  $display("time\t\tclk\tenable\treset\td\t|\tq");
  $display("-----------------------------------");
  $monitor("%g\t\t%b\t%b\t%b\t%b\t|\t%b",
    $time, clk, enable, reset, d, q);
  clk = 1;
  enable = 1;
  reset = 0;
  d = 0;
  #10 d = 1;
  #20 d = 0;
  #20 d = 1;
  #20 reset = 1;
  #10 reset = 0;
  #20 enable = 0;
  #10 d = 0;
  #10 d = 1;
  #10 d = 0;
  #10 enable = 1;
  #20;

  $display("\nFlip Flop Tipo D - 2 Bit");
  $display("time\t\tclk\tenable\treset\td\t|\tq");
  $display("-----------------------------------");
  $monitor("%g\t\t%b\t%b\t%b\t%b\t|\t%b",
    $time, clk, enable, reset, d2, q2);
  d2 = 0;
  reset = 1;
  #10 reset = 0;
  #10 d2 = 1;
  #20 d2 = 0;
  #20 d2 = 2;
  #20 reset = 1;
  #10 reset = 0;
  #20 enable = 0;
  #10 d2 = 3;
  #10 d2 = 1;
  #10 d2 = 0;
  #10 enable = 1;
  #10 d2 = 3;
  #10 d2 = 1;
  #10 d2 = 0;
  #20;

  $display("\nFlip Flop Tipo D - 4 Bit");
  $display("time\t\tclk\tenable\treset\td\t|\tq");
  $display("-----------------------------------");
  $monitor("%g\t\t%b\t%b\t%b\t%b\t|\t%b",
    $time, clk, enable, reset, d4, q4);
  d4 = 0;
  reset = 1;
  #10 reset = 0;
  #10 d4 = 1;
  #20 d4 = 0;
  #20 d4 = 2;
  #20 reset = 1;
  #10 reset = 0;
  #20 enable = 0;
  #10 d4 = 3;
  #10 d4 = 5;
  #10 d4 = 7;
  #10 enable = 1;
  #10 d4 = 3;
  #10 d4 = 8;
  #10 d4 = 10;
  #10 $finish;
  end

  initial begin
  $dumpfile("ejercicio1_tb.vcd");
  $dumpvars(0, ejercicio1_tb);
  end
endmodule // ejercicio1_tb

Lab09/Ejercicio1/ejercicio1_tb.vcd
$date
	Thu Oct 29 11:51:32 2020
$end
$version
	Icarus Verilog
$end
$timescale
	1ps
$end
$scope module ejercicio1_tb $end
$var wire 4 ! q4 [3:0] $end
$var wire 2 " q2 [1:0] $end
$var wire 1 # q $end
$var reg 1 $ clk $end
$var reg 1 % d $end
$var reg 2 & d2 [1:0] $end
$var reg 4 ' d4 [3:0] $end
$var reg 1 ( enable $end
$var reg 1 ) reset $end
$scope module D_Flip_Flop $end
$var wire 1 $ clk $end
$var wire 1 % d $end
$var wire 1 ( enable $end
$var wire 1 ) reset $end
$var reg 1 # q $end
$upscope $end
$scope module D_Flip_Flop_2bits $end
$var wire 1 $ clk $end
$var wire 2 * d [1:0] $end
$var wire 1 ( enable $end
$var wire 1 ) reset $end
$var wire 2 + q [1:0] $end
$scope module B0 $end
$var wire 1 $ clk $end
$var wire 1 , d $end
$var wire 1 ( enable $end
$var wire 1 ) reset $end
$var reg 1 - q $end
$upscope $end
$scope module B1 $end
$var wire 1 $ clk $end
$var wire 1 . d $end
$var wire 1 ( enable $end
$var wire 1 ) reset $end
$var reg 1 / q $end
$upscope $end
$upscope $end
$scope module D_Flip_Flop_4bits $end
$var wire 1 $ clk $end
$var wire 4 0 d [3:0] $end
$var wire 1 ( enable $end
$var wire 1 ) reset $end
$var wire 4 1 q [3:0] $end
$scope module B10 $end
$var wire 1 $ clk $end
$var wire 2 2 d [1:0] $end
$var wire 1 ( enable $end
$var wire 1 ) reset $end
$var wire 2 3 q [1:0] $end
$scope module B0 $end
$var wire 1 $ clk $end
$var wire 1 4 d $end
$var wire 1 ( enable $end
$var wire 1 ) reset $end
$var reg 1 5 q $end
$upscope $end
$scope module B1 $end
$var wire 1 $ clk $end
$var wire 1 6 d $end
$var wire 1 ( enable $end
$var wire 1 ) reset $end
$var reg 1 7 q $end
$upscope $end
$upscope $end
$scope module B32 $end
$var wire 1 $ clk $end
$var wire 2 8 d [1:0] $end
$var wire 1 ( enable $end
$var wire 1 ) reset $end
$var wire 2 9 q [1:0] $end
$scope module B0 $end
$var wire 1 $ clk $end
$var wire 1 : d $end
$var wire 1 ( enable $end
$var wire 1 ) reset $end
$var reg 1 ; q $end
$upscope $end
$scope module B1 $end
$var wire 1 $ clk $end
$var wire 1 < d $end
$var wire 1 ( enable $end
$var wire 1 ) reset $end
$var reg 1 = q $end
$upscope $end
$upscope $end
$upscope $end
$upscope $end
$enddefinitions $end
#0
$dumpvars
x=
x<
x;
x:
bx 9
bx 8
x7
x6
x5
x4
bx 3
bx 2
bx 1
bx 0
x/
x.
x-
x,
bx +
bx *
0)
1(
bx '
bx &
0%
1$
0#
bx "
bx !
$end
#5
0$
#10
1#
1$
1%
#15
0$
#20
1$
#25
0$
#30
0#
1$
0%
#35
0$
#40
1$
#45
0$
#50
1#
1$
1%
#55
0$
#60
1$
#65
0$
#70
05
b0 3
07
0;
b0 !
b0 1
b0 9
0=
0-
b0 "
b0 +
0/
0#
1$
1)
#75
0$
#80
1#
x/
bx "
bx +
x-
x=
bx 9
x;
x7
bx !
bx 1
bx 3
x5
1$
0)
#85
0$
#90
1$
#95
0$
#100
1$
0(
#105
0$
#110
1$
0%
#115
0$
#120
1$
1%
#125
0$
#130
1$
0%
#135
0$
#140
0#
1$
1(
#145
0$
#150
1$
#155
0$
#160
0/
b0 "
b0 +
0-
0=
b0 9
0;
07
b0 !
b0 1
b0 3
05
0.
0,
1$
1)
b0 &
b0 *
#165
0$
#170
x5
bx 3
x7
x;
bx !
bx 1
bx 9
x=
1$
0)
#175
0$
#180
b1 "
b1 +
1-
1,
1$
b1 &
b1 *
#185
0$
#190
1$
#195
0$
#200
b0 "
b0 +
0-
0,
1$
b0 &
b0 *
#205
0$
#210
1$
#215
0$
#220
b10 "
b10 +
1/
1.
1$
b10 &
b10 *
#225
0$
#230
1$
#235
0$
#240
b0 "
b0 +
0/
0=
b0 9
0;
07
b0 !
b0 1
b0 3
05
1$
1)
#245
0$
#250
x5
bx 3
x7
x;
bx !
bx 1
bx 9
x=
b10 "
b10 +
1/
1$
0)
#255
0$
#260
1$
#265
0$
#270
1$
0(
#275
0$
#280
1,
1$
b11 &
b11 *
#285
0$
#290
0.
1$
b1 &
b1 *
#295
0$
#300
0,
1$
b0 &
b0 *
#305
0$
#310
b0 "
b0 +
0/
1$
1(
#315
0$
#320
1/
b11 "
b11 +
1-
1.
1,
1$
b11 &
b11 *
#325
0$
#330
b1 "
b1 +
0/
0.
1$
b1 &
b1 *
#335
0$
#340
b0 "
b0 +
0-
0,
1$
b0 &
b0 *
#345
0$
#350
1$
#355
0$
#360
0<
0:
06
04
0=
b0 9
0;
07
b0 !
b0 1
b0 3
05
b0 8
b0 2
1$
1)
b0 '
b0 0
#365
0$
#370
1$
0)
#375
0$
#380
14
b1 2
1$
b1 '
b1 0
#385
0$
#390
b1 !
b1 1
b1 3
15
1$
#395
0$
#400
04
b0 2
1$
b0 '
b0 0
#405
0$
#410
b0 !
b0 1
b0 3
05
1$
#415
0$
#420
16
b10 2
1$
b10 '
b10 0
#425
0$
#430
b10 !
b10 1
b10 3
17
1$
#435
0$
#440
b0 !
b0 1
b0 3
07
1$
1)
#445
0$
#450
b10 !
b10 1
b10 3
17
1$
0)
#455
0$
#460
1$
#465
0$
#470
1$
0(
#475
0$
#480
14
b11 2
1$
b11 '
b11 0
#485
0$
#490
1:
06
b1 8
b1 2
1$
b101 '
b101 0
#495
0$
#500
16
b11 2
1$
b111 '
b111 0
#505
0$
#510
b11 3
15
b111 !
b111 1
b1 9
1;
1$
1(
#515
0$
#520
0:
b0 8
1$
b11 '
b11 0
#525
0$
#530
1<
06
04
b11 !
b11 1
b0 9
0;
b10 8
b0 2
1$
b1000 '
b1000 0
#535
0$
#540
16
b10 9
1=
07
b1000 !
b1000 1
b0 3
05
b10 2
1$
b1010 '
b1010 0
#545
0$
#550
b1010 !
b1010 1
b10 3
17
1$
