Lab09/Ejercicio1/Ejercicio1.v
module D_Flip_Flop (input clk, enable, reset, d,
                    output reg q);
  always @ (posedge clk, posedge reset, posedge enable)
    if (~enable)
      q = q;
    else if (reset)
      q = 0;
    else
      q = d;
endmodule // DFlip-Flop

module D_Flip_Flop_2bits (input clk, enable, reset,
                         input [1:0] d,
                         output [1:0] q);
  D_Flip_Flop B1(clk, enable, reset, d[1], q[1]);
  D_Flip_Flop B0(clk, enable, reset, d[0], q[0]);
endmodule // 2_Bit_D_Flip_Flop

module D_Flip_Flop_4bits (input  clk, enable, reset,
                          input [3:0] d,
                          output [3:0] q);
  D_Flip_Flop_2bits B32(clk, enable, reset, d[3:2], q[3:2]);
  D_Flip_Flop_2bits B10(clk, enable, reset, d[1:0], q[1:0]);
endmodule // D_Flip_Flop_4bits

Lab09/Ejercicio2/Ejercicio2.v
module T_Flip_Flop (input clk, enable, reset,
                    output q);
  wire d;
  assign d = ~q;

      D_Flip_Flop t(clk, enable, reset, d, q);

endmodule // T_Flip_Flop

Lab09/Ejercicio2/Ejercicio2_tb.v
module ejercicio2_tb ();
  reg clk, enable, reset;
  wire q;

  T_Flip_Flop T_Flip_Flop(clk, enable, reset, q);

  always begin
    #5 clk = ~clk;
  end

  initial begin
  $display("Flip Flop Tipo T");
  $display("time\t\tclk\tenable\treset\t|\tq");
  $display("-----------------------------------");
  $monitor("%g\t\t%b\t%b\t%b\t|\t%b",
    $time, clk, enable, reset, q);
  clk = 1;
  enable = 1;
  reset = 0;
  #5 reset = 1;
  #5 reset = 0;
  #50 enable = 0;
  #20 enable = 1;
  #50 $finish;
  end

  initial begin
  $dumpfile("ejercicio2_tb.vcd");
  $dumpvars(0, ejercicio2_tb);
  end

endmodule // ejercicio2_tb

Lab09/Ejercicio2/ejercicio2_tb.vcd
$date
	Fri Oct 30 23:19:52 2020
$end
$version
	Icarus Verilog
$end
$timescale
	1ps
$end
$scope module ejercicio2_tb $end
$var wire 1 ! q $end
$var reg 1 " clk $end
$var reg 1 # enable $end
$var reg 1 $ reset $end
$scope module T_Flip_Flop $end
$var wire 1 " clk $end
$var wire 1 % d $end
$var wire 1 # enable $end
$var wire 1 $ reset $end
$var wire 1 ! q $end
$scope module t $end
$var wire 1 " clk $end
$var wire 1 % d $end
$var wire 1 # enable $end
$var wire 1 $ reset $end
$var reg 1 ! q $end
$upscope $end
$upscope $end
$upscope $end
$enddefinitions $end
#0
$dumpvars
x%
0$
1#
1"
x!
$end
#5
1%
0!
1$
0"
#10
0%
1!
0$
1"
#15
0"
#20
1%
0!
1"
#25
0"
#30
0%
1!
1"
#35
0"
#40
1%
0!
1"
#45
0"
#50
0%
1!
1"
#55
0"
#60
1"
0#
#65
0"
#70
1"
#75
0"
#80
1%
0!
1"
1#
#85
0"
#90
0%
1!
1"
#95
0"
#100
1%
0!
1"
#105
0"
#110
0%
1!
1"
#115
0"
#120
1%
0!
1"
#125
0"
#130
0%
1!
1"
