Proyecto_2/TriState_buffer.v
module tri_state (input [3:0] a,
                  input s,
                  output [3:0] y);

    assign y = s ? a : 4'bzzzz;

endmodule

Lab10/Ejercicio2/ALU_Processor.v
module alu (input reset,
            input [3:0] a, b,
            input [2:0] f,
            output reg [3:0] y,
            output reg c_out, zero);

  reg [4:0] overflow_aid;

  parameter pass_a = 3'b000;
  parameter pass_b = 3'b010;
  parameter compare = 3'b001;
  parameter ADD = 3'b011;
  parameter NOR = 3'b100;

  always @(*) begin
    case(f)
      pass_a: y = a;
      pass_b: y = b;
      compare: begin
                overflow_aid = a-b;
                y = overflow_aid[3:0];
                c_out = overflow_aid[4];
                end
      ADD: begin
            overflow_aid = a+b;
            y = overflow_aid[3:0];
            c_out = overflow_aid[4];
           end
      NOR: y = a~|b;
      default: y = 3'b000;
    endcase

  if (y == 0)
    zero = 1;
    else
      zero = 0;

  if (reset == 1)
    c_out = 0;
      end
endmodule // alu

Lab10/Ejercicio2/D_Flip_Flop.v
module D_Flip_Flop_8(input clk, reset, enable,
									   input [7:0] d,
									   output reg [7:0] q);
	always@(posedge clk, posedge reset)
	if (reset) q <= 8'b0;
	else if (enable) q <= d;
endmodule

module D_Flip_Flop_4(input clk, reset, enable,
									   input [3:0] d,
									   output reg [3:0] q);
	always@(posedge clk, posedge reset)
	if (reset) q <= 3'b0;
	else if (enable) q <= d;
endmodule

Lab10/Ejercicio2/Ejercicio2.v
module ejercicio2(input clk, reset, enable_accu, enable_bus1, enable_bus2,
                   input [3:0] bus1_in,
                   input [2:0] f,
                   output zero,
                   output[3:0] bus2_out);
  wire [3:0] alu_out;
  wire c_out;
  wire [3:0] a, b;

  D_Flip_Flop_4 accumulator(clk, reset, enable_accu, alu_out, a);
  alu alu(reset, a, b, f, alu_out, c_out, zero);
  tri_state bus1(bus1_in, enable_bus1, b);
  tri_state bus2(alu_out, enable_bus2, bus2_out);
endmodule

Lab10/Ejercicio2/Ejercicio2_tb.v
module ejercicio2_tb();
  reg clk, reset, enable_accu, enable_bus1, enable_bus2;
  reg [3:0] bus1_in;
  reg[2:0] f;
  wire zero;
  wire [3:0] bus2_out;

  ejercicio2 ejercicio2 (clk, reset, enable_accu, enable_bus1, enable_bus2, bus1_in, f, zero, bus2_out);

    always begin
      #5 clk = ~clk;
    end

  initial begin
    $display("Ejercicio 1");
    $display("Time\t\tclk\treset en_accu en_bus1 en_bus2 bus1_in\tf\t|\tzero\tbus2_out");
    $display("------------------------------------------------------------------------| ---------------");
    $monitor("%g\t\t%b\t%b\t%b\t%b\t%b\t%b\t%b\t|\t%b\t%b\t",
      $time, clk, reset, enable_accu, enable_bus1, enable_bus2,
      bus1_in, f, zero, bus2_out);
    clk = 0; reset = 0; enable_accu = 1; enable_bus1 = 0; enable_bus2 = 0; bus1_in = 5; f=0;
    #5 reset = 1; enable_bus1 = 1; enable_bus2 = 1;
    #5 reset = 0;
    #20 f = 3'b010;
    #20 enable_bus1 = 0;
    #20 enable_bus1 = 1;
    #20 f = 3'b001;
    #10 f = 3'b011;
    #20 f = 3'b100;
    #20 enable_bus2 = 0;
    #10 enable_bus2 = 1; f = 3'b000;
    #50 $finish;
  end

  initial begin
    $dumpfile("ejercicio2_tb.vcd");
    $dumpvars(0, ejercicio2_tb);
    end
endmodule

Lab10/Ejercicio2/ejercicio2_tb.vcd
$date
	Sat Nov 07 22:09:21 2020
$end
$version
	Icarus Verilog
$end
$timescale
	1ps
$end
$scope module ejercicio2_tb $end
$var wire 1 ! zero $end
$var wire 4 " bus2_out [3:0] $end
$var reg 4 # bus1_in [3:0] $end
$var reg 1 $ clk $end
$var reg 1 % enable_accu $end
$var reg 1 & enable_bus1 $end
$var reg 1 ' enable_bus2 $end
$var reg 3 ( f [2:0] $end
$var reg 1 ) reset $end
$scope module ejercicio2 $end
$var wire 4 * bus1_in [3:0] $end
$var wire 1 $ clk $end
$var wire 1 % enable_accu $end
$var wire 1 & enable_bus1 $end
$var wire 1 ' enable_bus2 $end
$var wire 3 + f [2:0] $end
$var wire 1 ) reset $end
$var wire 1 ! zero $end
$var wire 1 , c_out $end
$var wire 4 - bus2_out [3:0] $end
$var wire 4 . b [3:0] $end
$var wire 4 / alu_out [3:0] $end
$var wire 4 0 a [3:0] $end
$scope module accumulator $end
$var wire 1 $ clk $end
$var wire 1 % enable $end
$var wire 1 ) reset $end
$var wire 4 1 d [3:0] $end
$var reg 4 2 q [3:0] $end
$upscope $end
$scope module alu $end
$var wire 4 3 a [3:0] $end
$var wire 3 4 f [2:0] $end
$var wire 1 ) reset $end
$var wire 4 5 b [3:0] $end
$var reg 1 , c_out $end
$var reg 5 6 overflow_aid [4:0] $end
$var reg 4 7 y [3:0] $end
$var reg 1 ! zero $end
$upscope $end
$scope module bus1 $end
$var wire 4 8 a [3:0] $end
$var wire 1 & s $end
$var wire 4 9 y [3:0] $end
$upscope $end
$scope module bus2 $end
$var wire 4 : a [3:0] $end
$var wire 1 ' s $end
$var wire 4 ; y [3:0] $end
$upscope $end
$upscope $end
$upscope $end
$enddefinitions $end
#0
$dumpvars
bz ;
bx :
bz 9
b101 8
bx 7
bx 6
bz 5
b0 4
bx 3
bx 2
bx 1
bx 0
bx /
bz .
bz -
x,
b0 +
b101 *
0)
b0 (
0'
0&
1%
0$
b101 #
bz "
0!
$end
#5
1!
b0 /
b0 1
b0 7
b0 :
b0 0
b0 2
b0 3
b0 "
b0 -
b0 ;
b101 .
b101 5
b101 9
0,
1'
1&
1)
1$
#10
0)
0$
#15
1$
#20
0$
#25
1$
#30
b101 "
b101 -
b101 ;
0!
b101 /
b101 1
b101 7
b101 :
0$
b10 (
b10 +
b10 4
#35
b101 0
b101 2
b101 3
1$
#40
0$
#45
1$
#50
bz "
bz -
bz ;
bz /
bz 1
bz 7
bz :
bz .
bz 5
bz 9
0$
0&
#55
bz 0
bz 2
bz 3
1$
#60
0$
#65
1$
#70
b101 "
b101 -
b101 ;
b101 /
b101 1
b101 7
b101 :
b101 .
b101 5
b101 9
0$
1&
#75
b101 0
b101 2
b101 3
1$
#80
0$
#85
1$
#90
b0 "
b0 -
b0 ;
1!
b0 /
b0 1
b0 7
b0 :
b0 6
0$
b1 (
b1 +
b1 4
#95
b1011 "
b1011 -
b1011 ;
0!
1,
b1011 /
b1011 1
b1011 7
b1011 :
b11011 6
b0 0
b0 2
b0 3
1$
#100
b101 "
b101 -
b101 ;
0,
b101 /
b101 1
b101 7
b101 :
b101 6
0$
b11 (
b11 +
b11 4
#105
b1010 "
b1010 -
b1010 ;
b1010 /
b1010 1
b1010 7
b1010 :
b1010 6
b101 0
b101 2
b101 3
1$
#110
0$
#115
b1111 "
b1111 -
b1111 ;
b1111 /
b1111 1
b1111 7
b1111 :
b1111 6
b1010 0
b1010 2
b1010 3
1$
#120
b0 "
b0 -
b0 ;
1!
b0 /
b0 1
b0 7
b0 :
0$
b100 (
b100 +
b100 4
#125
b1010 "
b1010 -
b1010 ;
0!
b1010 /
b1010 1
b1010 7
b1010 :
b0 0
b0 2
b0 3
1$
#130
0$
#135
b0 "
b0 -
b0 ;
1!
b0 /
b0 1
b0 7
b0 :
b1010 0
b1010 2
b1010 3
1$
#140
bz "
bz -
bz ;
0$
0'
#145
0!
b1010 /
b1010 1
b1010 7
b1010 :
b0 0
b0 2
b0 3
1$
#150
1!
b0 /
b0 1
b0 7
b0 :
b0 "
b0 -
b0 ;
0$
b0 (
b0 +
b0 4
1'
