Lab09/Ejercicio1/Ejercicio1.v
module D_Flip_Flop (input clk, enable, reset, d,
                    output reg q);
  always @ (posedge clk, posedge reset, posedge enable)
    if (~enable)
      q = q;
    else if (reset)
      q = 0;
    else
      q = d;
endmodule // DFlip-Flop

module D_Flip_Flop_2bits (input clk, enable, reset,
                         input [1:0] d,
                         output [1:0] q);
  D_Flip_Flop B1(clk, enable, reset, d[1], q[1]);
  D_Flip_Flop B0(clk, enable, reset, d[0], q[0]);
endmodule // 2_Bit_D_Flip_Flop

module D_Flip_Flop_4bits (input  clk, enable, reset,
                          input [3:0] d,
                          output [3:0] q);
  D_Flip_Flop_2bits B32(clk, enable, reset, d[3:2], q[3:2]);
  D_Flip_Flop_2bits B10(clk, enable, reset, d[1:0], q[1:0]);
endmodule // D_Flip_Flop_4bits

Lab09/Ejercicio3/Ejercicio3.v
module JK_Flip_Flop (input clk, enable, reset, j, k,
                     output q);
  wire q1, q2, w1, w2, d;

  assign q1 = ~q;
  assign q2 = q;

  assign w1 = j & q1;
  assign w2 = ~k & q2;

  assign d = w1|w2;

  D_Flip_Flop JK(clk, enable, reset, d, q);

endmodule

Lab09/Ejercicio3/Ejercicio3_tb.v
module ejercicio3_tb ();
  reg clk, enable, reset, j, k;
  wire q;

  JK_Flip_Flop JK_Flip_Flop(clk, enable, reset, j, k, q);

  always begin
    #5 clk = ~clk;
  end

  initial begin
  $display("Flip Flop Tipo JK");
  $display("time\t\tclk\tenable\treset\tj\tk\t|\tq");
  $display("---------------------------------------");
  $monitor("%g\t\t%b\t%b\t%b\t%b\t%b\t|\t%b",
    $time, clk, enable, reset, j, k, q);
  clk = 1;
  enable = 1;
  reset = 1;
  j = 0;
  k = 0;
  #5 reset = 0;
  #10 j = 1;
  #50 k = 1;
  #50 j = 0;
  #10 j = 1; k = 0;
  #10 j = 0;
  #30 k = 1;
  #50 $finish;
  end

  initial begin
  $dumpfile("ejercicio3_tb.vcd");
  $dumpvars(0, ejercicio3_tb);
  end

endmodule // ejercicio2_tb

Lab09/Ejercicio3/ejercicio3_tb.vcd
$date
	Fri Oct 30 23:20:40 2020
$end
$version
	Icarus Verilog
$end
$timescale
	1ps
$end
$scope module ejercicio3_tb $end
$var wire 1 ! q $end
$var reg 1 " clk $end
$var reg 1 # enable $end
$var reg 1 $ j $end
$var reg 1 % k $end
$var reg 1 & reset $end
$scope module JK_Flip_Flop $end
$var wire 1 " clk $end
$var wire 1 ' d $end
$var wire 1 # enable $end
$var wire 1 $ j $end
$var wire 1 % k $end
$var wire 1 ( q1 $end
$var wire 1 ) q2 $end
$var wire 1 & reset $end
$var wire 1 * w1 $end
$var wire 1 + w2 $end
$var wire 1 ! q $end
$scope module JK $end
$var wire 1 " clk $end
$var wire 1 ' d $end
$var wire 1 # enable $end
$var wire 1 & reset $end
$var reg 1 ! q $end
$upscope $end
$upscope $end
$upscope $end
$enddefinitions $end
#0
$dumpvars
0+
0*
0)
1(
0'
1&
0%
0$
1#
1"
0!
$end
#5
0&
0"
#10
1"
#15
1'
1*
0"
1$
#20
0*
1+
0(
1)
1!
1"
#25
0"
#30
1"
#35
0"
#40
1"
#45
0"
#50
1"
#55
0"
#60
1"
#65
0'
0+
0"
1%
#70
1'
1*
1(
0)
0!
1"
#75
0"
#80
0'
0*
0(
1)
1!
1"
#85
0"
#90
1'
1*
1(
0)
0!
1"
#95
0"
#100
0'
0*
0(
1)
1!
1"
#105
0"
#110
1'
1*
1(
0)
0!
1"
#115
0'
0*
0"
0$
#120
1"
#125
1'
1*
0"
0%
1$
#130
0*
1+
0(
1)
1!
1"
#135
0"
0$
#140
1"
#145
0"
#150
1"
#155
0"
#160
1"
#165
0'
0+
0"
1%
#170
1(
0)
0!
1"
