Proyecto/Proyecto1.v
module antirebote(input clk, reset, a,
                  output y);
  reg state, nextstate;
  parameter  S0 = 1'b0;
  parameter  S1 = 1'b1;

  always @ (posedge clk, posedge reset)
    if (reset) state <= S0;
    else       state <= nextstate;

  //States
  always @(*)
    case(state)
      S0:  if (a) nextstate = S1;
           else   nextstate = S0;
      S1: if(~a) nextstate = S0;
          else   nextstate = S1;
    endcase
  //output
  assign y = (a & state==S0);
endmodule



module alarm (input clk, reset, a,
              output y);

reg [1:0] state, nextstate;

parameter S0 = 2'b00;
parameter S1 = 2'b01;
parameter S2 = 2'b10;
parameter S3 = 2'b11;

always @ (posedge clk, posedge reset)
  if (reset) state <= S0;
  else       state <= nextstate;

//States
always @ ( * )
  case(state)
    S0: if(a) nextstate = S1;
        else  nextstate = S0;
    S1: if(a) nextstate = S2;
        else  nextstate = S0;
    S2: if(a) nextstate = S3;
        else  nextstate = S0;
    S3: if(a) nextstate = S2;
        else  nextstate = S0;
  endcase

//output
assign y = (a & state == S3);
endmodule // alarm

//Movement
module movement(input clk, reset, l_in, r_in,
                output [2:0] state_out);

  reg [2:0] state, nextstate;
  parameter S0 = 3'b000;
  parameter L1 = 3'b001;
  parameter L2 = 3'b010;
  parameter L3 = 3'b011;
  parameter R1 = 3'b100;
  parameter R2 = 3'b101;
  parameter R3 = 3'b110;
  parameter RE = 3'b111;

  antirebote al(clk, reset, l_in, l_out);
  antirebote ar(clk, reset, r_in, r_out);

  always @ ( posedge clk, posedge reset)
    if (reset) state <= S0;
    else       state <= nextstate;

  //states
  always @ (*)
    case(state)
    S0: if (l_out&~r_out) nextstate = L1;
        else if (~l_out&r_out) nextstate = R1;
        else      nextstate = S0;
    L1: if (l_out&~r_out) nextstate = L2;
        else if (~l_out&r_out) nextstate = S0;
        else      nextstate = L1;
    L2: if (l_out&~r_out) nextstate = L3;
        else if (~l_out&r_out) nextstate = L1;
        else      nextstate = L2;
    L3: if (~l_out&r_out) nextstate = L2;
        else      nextstate = L3;
    R1: if (l_out&~r_out) nextstate = S0;
        else if (~l_out&r_out) nextstate = R2;
        else      nextstate = R1;
    R2: if (l_out&~r_out) nextstate = R1;
        else if (~l_out&r_out) nextstate = R3;
        else      nextstate = R2;
    R3: if (l_out&~r_out) nextstate = R2;
        else      nextstate = R3;
    endcase

  //output
  assign state_out = state;
endmodule

//ENGINE
module engine(input clk, reset, b_in, f_in,
              output [1:0] state_out);

  reg[1:0] state, nextstate;
  parameter  S0 = 2'b00;
  parameter  F1 = 2'b01;
  parameter  F2 = 2'b11;
  parameter  B1 = 2'b10;

  antirebote ab(clk, reset, b_in, b_out);
  antirebote af(clk, reset, f_in, f_out);

  always @ ( posedge clk, posedge reset)
    if (reset) state <= S0;
    else       state <= nextstate;

  //states
  always @ (*)
    case(state)
    S0: if (b_out&~f_out) nextstate = B1;
        else if (~b_out&f_out) nextstate = F1;
        else              nextstate = S0;
    B1: if (~b_out&f_out) nextstate = S0;
        else              nextstate = B1;
    F1: if (b_out&~f_out) nextstate = S0;
        else if (~b_out&f_out) nextstate = F2;
        else              nextstate = F1;
    F2: if (b_out&~f_out) nextstate = F1;
        else              nextstate = F2;
    endcase

  //output
  assign state_out = state;
endmodule

Proyecto/Elementos_tb.v
module global;
  reg clk = 1'b0;
  reg reset = 1'b0;
endmodule
module testbench_alarm();
  reg a;
  wire y;
  alarm alarm(global.clk, global.reset, a, y);

  always begin
    #5 global.clk = ~global.clk;
  end
  initial begin
    $display("time\t\tclk\treset\ta\t|\ty");
    $display("--------------------------------");
    $monitor("%g\t\t%b\t%b\t%b\t|\t%b",
      $time, global.clk, global.reset, a, y);
    global.clk = 1;
    global.reset = 0;
    a = 0;
    #5 global.reset = 1;
    #10 global.reset = 0;
    #10 a = 1;
    #100 a = 0;
  end

  initial begin
    $dumpfile("Elementos_tb.vcd");
    $dumpvars(0, testbench_alarm);
  end
endmodule

//MOVEMENT
module testbench_movement();
  reg l_in, r_in;
  wire [2:0] state_out;
  movement left_right (global.clk, global.reset, l_in, r_in, state_out);

  initial begin
    #150;
    $display("\ntime\t\tclk\treset\tl_in\tr_in\t|\tstate_out");
    $display("--------------------------------");
    $monitor("%g\t\t%b\t%b\t%b\t%b\t|\t%b",
      $time, global.clk, global.reset, l_in, r_in, state_out);
    global.reset = 0;
    l_in = 0;
    r_in = 0;
    #5 global.reset = 1;
    #10 global.reset = 0;
    #10 l_in = 1;
    #10 l_in = 0;
    #10 l_in = 1;
    #10 l_in = 0;
    #10 l_in = 1;
    #10 l_in = 0;
    #10 l_in = 1;
    #10 l_in = 0;
    #10 r_in = 1;
    #10 r_in = 0;
    #10 r_in = 1;
    #10 r_in = 0;
    #10 r_in = 1;
    #10 r_in = 0;
    #10 r_in = 1;
    #10 r_in = 0;
    #10 r_in = 1;
    #10 r_in = 0;
    #10 r_in = 1;
    #10 r_in = 0;
    #10 r_in = 1;
    #10 r_in = 0;
  end

  initial begin
    $dumpfile("Elementos_tb.vcd");
    $dumpvars(0, testbench_movement);
  end
endmodule

//engine
module testbench_engine ();
  reg b_in, f_in;
  wire [1:0] state_out;
  engine engine(global.clk, global.reset, b_in, f_in, state_out);

  initial begin
    #400;
    $display("\ntime\t\tclk\treset\tb_in\tf_in\t|\tstate_out");
    $display("--------------------------------");
    $monitor("%g\t\t%b\t%b\t%b\t%b\t|\t%b",
      $time, global.clk, global.reset, b_in, f_in, state_out);
    global.reset = 0;
    b_in = 0;
    f_in = 0;
    #5 global.reset = 1;
    #10 global.reset = 0;
    #10 b_in = 1;
    #10 b_in = 0;
    #10 b_in = 1;
    #10 b_in = 0;
    #10 f_in = 1;
    #10 f_in = 0;
    #10 f_in = 1;
    #10 f_in = 0;
    #10 f_in = 1;
    #10 f_in = 0;
    #10 f_in = 1;
    #10 f_in = 0;
    #30 $finish;
  end

  initial begin
    $dumpfile("Elementos_tb.vcd");
    $dumpvars(0,testbench_engine);
  end
endmodule // engine

Proyecto/Elementos_tb.vcd
$date
	Sat Oct 10 21:00:52 2020
$end
$version
	Icarus Verilog
$end
$timescale
	1ps
$end
$scope module testbench_alarm $end
$var wire 1 ! y $end
$var reg 1 " a $end
$scope module alarm $end
$var wire 1 " a $end
$var wire 1 # clk $end
$var wire 1 $ reset $end
$var wire 1 ! y $end
$var reg 2 % nextstate [1:0] $end
$var reg 2 & state [1:0] $end
$upscope $end
$upscope $end
$scope module testbench_engine $end
$var wire 2 ' state_out [1:0] $end
$var reg 1 ( b_in $end
$var reg 1 ) f_in $end
$scope module engine $end
$var wire 1 ( b_in $end
$var wire 1 # clk $end
$var wire 1 ) f_in $end
$var wire 1 $ reset $end
$var wire 2 * state_out [1:0] $end
$var wire 1 + f_out $end
$var wire 1 , b_out $end
$var reg 2 - nextstate [1:0] $end
$var reg 2 . state [1:0] $end
$scope module ab $end
$var wire 1 ( a $end
$var wire 1 # clk $end
$var wire 1 $ reset $end
$var wire 1 , y $end
$var reg 1 / nextstate $end
$var reg 1 0 state $end
$upscope $end
$scope module af $end
$var wire 1 ) a $end
$var wire 1 # clk $end
$var wire 1 $ reset $end
$var wire 1 + y $end
$var reg 1 1 nextstate $end
$var reg 1 2 state $end
$upscope $end
$upscope $end
$upscope $end
$scope module testbench_movement $end
$var wire 3 3 state_out [2:0] $end
$var reg 1 4 l_in $end
$var reg 1 5 r_in $end
$scope module left_right $end
$var wire 1 # clk $end
$var wire 1 4 l_in $end
$var wire 1 5 r_in $end
$var wire 1 $ reset $end
$var wire 3 6 state_out [2:0] $end
$var wire 1 7 r_out $end
$var wire 1 8 l_out $end
$var reg 3 9 nextstate [2:0] $end
$var reg 3 : state [2:0] $end
$scope module al $end
$var wire 1 4 a $end
$var wire 1 # clk $end
$var wire 1 $ reset $end
$var wire 1 8 y $end
$var reg 1 ; nextstate $end
$var reg 1 < state $end
$upscope $end
$scope module ar $end
$var wire 1 5 a $end
$var wire 1 # clk $end
$var wire 1 $ reset $end
$var wire 1 7 y $end
$var reg 1 = nextstate $end
$var reg 1 > state $end
$upscope $end
$upscope $end
$upscope $end
$enddefinitions $end
#0
$dumpvars
x>
x=
x<
x;
bx :
bx 9
x8
x7
bx 6
x5
x4
bx 3
x2
x1
x0
x/
bx .
bx -
x,
x+
bx *
x)
x(
bx '
bx &
bx %
0$
1#
0"
0!
$end
#5
0/
01
b0 -
0;
0=
b0 9
b0 %
00
02
b0 '
b0 *
b0 .
0<
0>
b0 3
b0 6
b0 :
b0 &
1$
0#
#10
1#
#15
0#
0$
#20
1#
#25
b1 %
0#
1"
#30
b10 %
b1 &
1#
#35
0#
#40
b11 %
b10 &
1#
#45
0#
#50
b10 %
1!
b11 &
1#
#55
0#
#60
b11 %
0!
b10 &
1#
#65
0#
#70
b10 %
1!
b11 &
1#
#75
0#
#80
b11 %
0!
b10 &
1#
#85
0#
#90
b10 %
1!
b11 &
1#
#95
0#
#100
b11 %
0!
b10 &
1#
#105
0#
#110
b10 %
1!
b11 &
1#
#115
0#
#120
b11 %
0!
b10 &
1#
#125
b0 %
0#
0"
#130
b0 &
1#
#135
0#
#140
1#
#145
0#
#150
07
08
1#
05
04
#155
0#
1$
#160
1#
#165
0#
0$
#170
1#
#175
b1 9
18
1;
0#
14
#180
08
b1 9
b1 3
b1 6
b1 :
1<
1#
#185
0;
0#
04
#190
0<
1#
#195
b10 9
18
1;
0#
14
#200
08
b10 9
b10 3
b10 6
b10 :
1<
1#
#205
0;
0#
04
#210
0<
1#
#215
b11 9
18
1;
0#
14
#220
08
b11 3
b11 6
b11 :
1<
1#
#225
0;
0#
04
#230
0<
1#
#235
18
1;
0#
14
#240
08
1<
1#
#245
0;
0#
04
#250
0<
1#
#255
b10 9
17
1=
0#
15
#260
07
b10 9
b10 3
b10 6
b10 :
1>
1#
#265
0=
0#
05
#270
0>
1#
#275
b1 9
17
1=
0#
15
#280
07
b1 9
b1 3
b1 6
b1 :
1>
1#
#285
0=
0#
05
#290
0>
1#
#295
b0 9
17
1=
0#
15
#300
07
b0 9
b0 3
b0 6
b0 :
1>
1#
#305
0=
0#
05
#310
0>
1#
#315
b100 9
17
1=
0#
15
#320
07
b100 9
b100 3
b100 6
b100 :
1>
1#
#325
0=
0#
05
#330
0>
1#
#335
b101 9
17
1=
0#
15
#340
07
b101 9
b101 3
b101 6
b101 :
1>
1#
#345
0=
0#
05
#350
0>
1#
#355
b110 9
17
1=
0#
15
#360
07
b110 3
b110 6
b110 :
1>
1#
#365
0=
0#
05
#370
0>
1#
#375
17
1=
0#
15
#380
07
1>
1#
#385
0=
0#
05
#390
0>
1#
#395
0#
#400
0+
0,
1#
0)
0(
#405
b0 9
b0 3
b0 6
b0 :
0#
1$
#410
1#
#415
0#
0$
#420
1#
#425
b10 -
1,
1/
0#
1(
#430
0,
b10 '
b10 *
b10 .
10
1#
#435
0/
0#
0(
#440
00
1#
#445
1,
1/
0#
1(
#450
0,
10
1#
#455
0/
0#
0(
#460
00
1#
#465
b0 -
1+
11
0#
1)
#470
0+
b0 -
b0 '
b0 *
b0 .
12
1#
#475
01
0#
0)
#480
02
1#
#485
b1 -
1+
11
0#
1)
#490
0+
b1 -
b1 '
b1 *
b1 .
12
1#
#495
01
0#
0)
#500
02
1#
#505
b11 -
1+
11
0#
1)
#510
0+
b11 '
b11 *
b11 .
12
1#
#515
01
0#
0)
#520
02
1#
#525
1+
11
0#
1)
#530
0+
12
1#
#535
01
0#
0)
#540
02
1#
