Proyecto/Proyecto1.v
module antirebote(input clk, reset, a,
                  output y);
  reg state, nextstate;
  parameter  S0 = 1'b0;
  parameter  S1 = 1'b1;

  always @ (posedge clk, posedge reset)
    if (reset) state <= S0;
    else       state <= nextstate;

  //States
  always @(*)
    case(state)
      S0:  if (a) nextstate = S1;
           else   nextstate = S0;
      S1: if(~a) nextstate = S0;
          else   nextstate = S1;
    endcase
  //output
  assign y = (a & state==S0);
endmodule



module alarm (input clk, reset, a,
              output y);

reg [1:0] state, nextstate;

parameter S0 = 2'b00;
parameter S1 = 2'b01;
parameter S2 = 2'b10;
parameter S3 = 2'b11;

always @ (posedge clk, posedge reset)
  if (reset) state <= S0;
  else       state <= nextstate;

//States
always @ ( * )
  case(state)
    S0: if(a) nextstate = S1;
        else  nextstate = S0;
    S1: if(a) nextstate = S2;
        else  nextstate = S0;
    S2: if(a) nextstate = S3;
        else  nextstate = S0;
    S3: if(a) nextstate = S2;
        else  nextstate = S0;
  endcase

//output
assign y = (a & state == S3);
endmodule // alarm

//Movement
module movement(input clk, reset, l_in, r_in,
                output [2:0] state_out);

  wire l, r;

  reg [2:0] state, nextstate;
  parameter S0 = 3'b000;
  parameter L1 = 3'b001;
  parameter L2 = 3'b010;
  parameter L3 = 3'b011;
  parameter R1 = 3'b100;
  parameter R2 = 3'b101;
  parameter R3 = 3'b110;
  parameter RE = 3'b111;

  antirebote al(clk, reset, l_in, l_out);
  antirebote ar(clk, reset, r_in, r_out);

  always @ ( posedge clk, posedge reset)
    if (reset) state <= S0;
    else       state <= nextstate;

  //states
  always @ (*)
    case(state)
    S0: if (l_out&~r_out) nextstate = L1;
        else if (~l_out&r_out) nextstate = R1;
        else      nextstate = S0;
    L1: if (l_out&~r_out) nextstate = L2;
        else if (~l_out&r_out) nextstate = S0;
        else      nextstate = L1;
    L2: if (l_out&~r_out) nextstate = L3;
        else if (~l_out&r_out) nextstate = L1;
        else      nextstate = L2;
    L3: if (~l_out&r_out) nextstate = L2;
        else      nextstate = L3;
    R1: if (l_out&~r_out) nextstate = S0;
        else if (~l_out&r_out) nextstate = R2;
        else      nextstate = R1;
    R2: if (l_out&~r_out) nextstate = R1;
        else if (~l_out&r_out) nextstate = R3;
        else      nextstate = R2;
    R3: if (l_out&~r_out) nextstate = R2;
        else      nextstate = R3;
    endcase

  //output
  assign state_out = state;
endmodule

Proyecto/Proyecto1_tb.v
module testbench_alarm();
  reg clk, reset, a;
  wire y;
  alarm alarm(clk, reset, a, y);

  always begin
    #5 clk = ~clk;
  end
  initial begin
    $display("time\t clk reset state a next y");
    $display("--------------------------------");
    $monitor("%g\t %b %b %b, %b",
      $time, clk, reset, a, y);
    clk = 1;
    reset = 0;
    a = 0;
    #5 reset = 1;
    #10 reset = 0;
    #10 a = 1;
    #100 a = 0;
    #50;
  end

  initial begin
		$dumpfile("Proyecto1_tb.vcd");
		$dumpvars(0,testbench_alarm);
	end
endmodule

//MOVEMENT
module testbench_movement();
  reg clk, reset, l_in, r_in;
  wire state;
  movement left_right (clk, reset, l_in, r_in, state_out);

  always begin
    #5 clk = ~clk;
  end

  initial begin
    $display("time\t clk reset l_in r_in state_out");
    $display("--------------------------------");
    $monitor("%g\t %b %b %b, %b %b",
      $time, clk, reset, l_in, r_in, state_out);
    clk = 1;
    reset = 0;
    l_in = 0;
    r_in = 0;
    #5 reset = 1;
    #10 reset = 0;
    #10 l_in = 1;
    #10 l_in = 0;
    #10 l_in = 1;
    #10 l_in = 0;
    #10 l_in = 1;
    #10 l_in = 0;
    #10 l_in = 1;
    #10 l_in = 0;
    #10 r_in = 1;
    #10 r_in = 0;
    #10 r_in = 1;
    #10 r_in = 0;
    #10 r_in = 1;
    #10 r_in = 0;
    #10 r_in = 1;
    #10 r_in = 0;
    #10 r_in = 1;
    #10 r_in = 0;
    #10 r_in = 1;
    #10 r_in = 0;
    #10 r_in = 1;
    #10 r_in = 0;
    #100 $finish;
  end

  initial begin
    $dumpfile("Proyecto1_tb.vcd");
    $dumpvars(0,testbench_movement);
  end
endmodule

Proyecto/Proyecto1_tb.vcd
$date
	Sat Oct 10 17:55:07 2020
$end
$version
	Icarus Verilog
$end
$timescale
	1ps
$end
$scope module testbench_alarm $end
$var wire 1 ! y $end
$var reg 1 " a $end
$var reg 1 # clk $end
$var reg 1 $ reset $end
$scope module alarm $end
$var wire 1 " a $end
$var wire 1 # clk $end
$var wire 1 $ reset $end
$var wire 1 ! y $end
$var reg 2 % nextstate [1:0] $end
$var reg 2 & state [1:0] $end
$upscope $end
$upscope $end
$scope module testbench_movement $end
$var wire 1 ' state_out $end
$var reg 1 ( clk $end
$var reg 1 ) l_in $end
$var reg 1 * r_in $end
$var reg 1 + reset $end
$scope module left_right $end
$var wire 1 ( clk $end
$var wire 1 ) l_in $end
$var wire 1 * r_in $end
$var wire 1 + reset $end
$var wire 3 , state_out [2:0] $end
$var wire 1 - r_out $end
$var wire 1 . l_out $end
$var reg 3 / nextstate [2:0] $end
$var reg 3 0 state [2:0] $end
$scope module al $end
$var wire 1 ) a $end
$var wire 1 ( clk $end
$var wire 1 + reset $end
$var wire 1 . y $end
$var reg 1 1 nextstate $end
$var reg 1 2 state $end
$upscope $end
$scope module ar $end
$var wire 1 * a $end
$var wire 1 ( clk $end
$var wire 1 + reset $end
$var wire 1 - y $end
$var reg 1 3 nextstate $end
$var reg 1 4 state $end
$upscope $end
$upscope $end
$upscope $end
$enddefinitions $end
#0
$dumpvars
x4
x3
x2
x1
bx 0
bx /
0.
0-
bx ,
0+
0*
0)
1(
x'
bx &
bx %
0$
1#
0"
0!
$end
#5
b0 /
0'
03
01
b0 %
b0 ,
b0 0
04
02
b0 &
1+
0(
1$
0#
#10
1(
1#
#15
0(
0#
0+
0$
#20
1(
1#
#25
b1 /
1.
11
b1 %
0(
0#
1)
1"
#30
0.
b1 /
1'
b10 %
12
b1 ,
b1 0
b1 &
1(
1#
#35
01
0(
0#
0)
#40
b11 %
02
b10 &
1(
1#
#45
b10 /
1.
11
0(
0#
1)
#50
0.
b10 /
0'
b10 %
1!
12
b10 ,
b10 0
b11 &
1(
1#
#55
01
0(
0#
0)
#60
b11 %
0!
02
b10 &
1(
1#
#65
b11 /
1.
11
0(
0#
1)
#70
0.
1'
b10 %
1!
12
b11 ,
b11 0
b11 &
1(
1#
#75
01
0(
0#
0)
#80
b11 %
0!
02
b10 &
1(
1#
#85
1.
11
0(
0#
1)
#90
0.
b10 %
1!
12
b11 &
1(
1#
#95
01
0(
0#
0)
#100
b11 %
0!
02
b10 &
1(
1#
#105
b10 /
1-
13
0(
0#
1*
#110
0-
b10 /
0'
b10 %
1!
14
b10 ,
b10 0
b11 &
1(
1#
#115
03
0(
0#
0*
#120
b11 %
0!
04
b10 &
1(
1#
#125
b1 /
1-
13
b0 %
0(
0#
1*
0"
#130
0-
b1 /
1'
14
b1 ,
b1 0
b0 &
1(
1#
#135
03
0(
0#
0*
#140
04
1(
1#
#145
b0 /
1-
13
0(
0#
1*
#150
0-
b0 /
0'
14
b0 ,
b0 0
1(
1#
#155
03
0(
0#
0*
#160
04
1(
1#
#165
b100 /
1-
13
0(
0#
1*
#170
0-
b100 /
14
b100 ,
b100 0
1(
1#
#175
03
0(
0#
0*
#180
04
1(
1#
#185
b101 /
1-
13
0(
0#
1*
#190
0-
b101 /
1'
14
b101 ,
b101 0
1(
1#
#195
03
0(
0#
0*
#200
04
1(
1#
#205
b110 /
1-
13
0(
0#
1*
#210
0-
0'
14
b110 ,
b110 0
1(
1#
#215
03
0(
0#
0*
#220
04
1(
1#
#225
1-
13
0(
0#
1*
#230
0-
14
1(
1#
#235
03
0(
0#
0*
#240
04
1(
1#
